arrow_cache_mcp/__init__.py
arrow_cache_mcp-0.1.1.dist-info/METADATA
arrow_cache_mcp-0.1.1.dist-info/WHEEL
arrow_cache_mcp-0.1.1.dist-info/entry_points.txt
arrow_cache_mcp-0.1.1.dist-info/RECORD
