Metadata-Version: 2.4
Name: arrow-cache-mcp
Version: 0.1.1
Summary: DataScience MCP with Apache Arrow-based cache for efficient data handling
Author-email: Pranav Satessh <pranav.sateesh@usi.ch>
Requires-Python: >=3.9
Requires-Dist: anthropic>=0.4.0
Requires-Dist: arrow-cache>=0.2.0
Requires-Dist: duckdb>=0.8.0
Requires-Dist: matplotlib>=3.5.0
Requires-Dist: numpy>=1.22.0
Requires-Dist: pandas>=1.5.0
Requires-Dist: psutil>=5.9.0
Requires-Dist: pyarrow>=11.0.0
Requires-Dist: tabulate>=0.9.0
Provides-Extra: geospatial
Requires-Dist: geopandas>=0.12.0; extra == 'geospatial'
Requires-Dist: shapely>=2.0.0; extra == 'geospatial'
Provides-Extra: viz
Requires-Dist: plotly>=5.10.0; extra == 'viz'
